say_hello_pkg/__init__.py
say_hello_pkg/say_hello.py
say_hello_pkg-0.1.0.dist-info/LICENSE
say_hello_pkg-0.1.0.dist-info/METADATA
say_hello_pkg-0.1.0.dist-info/WHEEL
say_hello_pkg-0.1.0.dist-info/top_level.txt
say_hello_pkg-0.1.0.dist-info/RECORD
