Metadata-Version: 2.1
Name: say-hello-pkg
Version: 0.1.0
Summary: an example for teaching how to publish a Python package
Home-page: https://github.com/pypa/sampleproject
Author: james Lu
License: UNKNOWN
Platform: UNKNOWN
Classifier: Programming Language :: Python :: 3
Classifier: License :: OSI Approved :: MIT License
Classifier: Operating System :: OS Independent
